README.md
setup.py
djangocheck/__init__.py
djangocheck/djangocheck.py
djangocheck.egg-info/PKG-INFO
djangocheck.egg-info/SOURCES.txt
djangocheck.egg-info/dependency_links.txt
djangocheck.egg-info/not-zip-safe
djangocheck.egg-info/requires.txt
djangocheck.egg-info/top_level.txt