Metadata-Version: 1.0
Name: djangocheck
Version: 0.2
Summary: Deploy checker for Django
Home-page: https://github.com/echiesse/django-check
Author: Eric Chiesse
Author-email: techiesse@gmail.com
License: MIT
Platform: UNKNOWN
